ff_sqlalchemy/__init__.py
ff_sqlalchemy/context.py
ff_sqlalchemy/orm/__init__.py
ff_sqlalchemy/orm/base_model.py
ff_sqlalchemy/session/__init__.py
ff_sqlalchemy/session/session.py
ff_sqlalchemy/session/session_proxy.py
ff_sqlalchemy/session/asyncio/__init__.py
ff_sqlalchemy/session/asyncio/session.py
ff_sqlalchemy/session/asyncio/session_proxy.py
ff_sqlalchemy/types/__init__.py
ff_sqlalchemy/types/db_str_py_enum.py
ff_sqlalchemy-0.1.0.dist-info/METADATA
ff_sqlalchemy-0.1.0.dist-info/WHEEL
ff_sqlalchemy-0.1.0.dist-info/top_level.txt
ff_sqlalchemy-0.1.0.dist-info/RECORD
