Metadata-Version: 2.4
Name: ff-sqlalchemy
Version: 0.1.0
Summary: A simple sqlalchemy library.
Home-page: https://github.com/itsanr-oris/ff-sqlalchemy
Author: foris.feng
Author-email: us@f-oris.me
License: MIT
Project-URL: Bug Tracker, https://github.com/itsanr-oris/ff-sqlalchemy/issues
Project-URL: Source Code, https://github.com/itsanr-oris/ff-sqlalchemy
Keywords: sqlalchemy,orm,database,db session
Classifier: Programming Language :: Python :: 3
Classifier: Programming Language :: Python :: 3.6
Classifier: Programming Language :: Python :: 3.7
Classifier: Programming Language :: Python :: 3.8
Classifier: Programming Language :: Python :: 3.9
Classifier: Programming Language :: Python :: 3.10
Classifier: Programming Language :: Python :: 3.11
Classifier: Programming Language :: Python :: 3.12
Classifier: Programming Language :: Python :: 3.13
Classifier: License :: OSI Approved :: MIT License
Classifier: Operating System :: OS Independent
Requires-Python: >=3.6
Requires-Dist: sqlalchemy
Requires-Dist: contextvars; python_version < "3.7"
Dynamic: requires-python
